<ROWSET> 
<TABLE NAME="SAP_OB_PATIENT">
<COLUMNS>
<COLUMN NAME="MESSAGE_CONTROL_ID" DATA_TYPE="VARCHAR2"></COLUMN>
<COLUMN NAME="ADDITIONAL_PARTICULARS" DATA_TYPE="VARCHAR2"></COLUMN>
<COLUMN NAME="REFERENCE1" DATA_TYPE="VARCHAR2"></COLUMN>
<COLUMN NAME="REFERENCE2" DATA_TYPE="VARCHAR2"></COLUMN>
<COLUMN NAME="REFERENCE3" DATA_TYPE="VARCHAR2"></COLUMN>
<COLUMN NAME="PROFIT_CENTER" DATA_TYPE="VARCHAR2"></COLUMN>
<COLUMN NAME="BUSINESS_PLACE" DATA_TYPE="VARCHAR2"></COLUMN>
<COLUMN NAME="DOCUMENT_TYPE" DATA_TYPE="VARCHAR2"></COLUMN>
<COLUMN NAME="COMPANYCD" DATA_TYPE="VARCHAR2"></COLUMN>
<COLUMN NAME="LOCATIONCD" DATA_TYPE="VARCHAR2"></COLUMN>
<COLUMN NAME="UMRNO" DATA_TYPE="VARCHAR2"></COLUMN>
<COLUMN NAME="PATIENTTITLE" DATA_TYPE="VARCHAR2"></COLUMN>
<COLUMN NAME="FIRSTNAME" DATA_TYPE="VARCHAR2"></COLUMN>
<COLUMN NAME="MIDDLENAME" DATA_TYPE="VARCHAR2"></COLUMN>
<COLUMN NAME="LASTNAME" DATA_TYPE="VARCHAR2"></COLUMN>
<COLUMN NAME="PATIENTNAME" DATA_TYPE="VARCHAR2"></COLUMN>
<COLUMN NAME="GUARDIANREL" DATA_TYPE="VARCHAR2"></COLUMN>
<COLUMN NAME="FATHERNAME" DATA_TYPE="VARCHAR2"></COLUMN>
<COLUMN NAME="MOTHERNAME" DATA_TYPE="VARCHAR2"></COLUMN>
<COLUMN NAME="GENDER" DATA_TYPE="CHAR"></COLUMN>
<COLUMN NAME="DOB" DATA_TYPE="DATE"></COLUMN>
<COLUMN NAME="MARITALSTATUS" DATA_TYPE="CHAR"></COLUMN>
<COLUMN NAME="OCCUPATION" DATA_TYPE="VARCHAR2"></COLUMN>
<COLUMN NAME="SS_PP_NO" DATA_TYPE="VARCHAR2"></COLUMN>
<COLUMN NAME="RELIGION" DATA_TYPE="VARCHAR2"></COLUMN>
<COLUMN NAME="NATIONALITY" DATA_TYPE="VARCHAR2"></COLUMN>
<COLUMN NAME="CREATEBY" DATA_TYPE="VARCHAR2"></COLUMN>
<COLUMN NAME="CREATEDT" DATA_TYPE="DATE"></COLUMN>
<COLUMN NAME="MODIFYBY" DATA_TYPE="VARCHAR2"></COLUMN>
<COLUMN NAME="MODIFYDT" DATA_TYPE="DATE"></COLUMN>
<COLUMN NAME="ISVIP" DATA_TYPE="VARCHAR2"></COLUMN>
<COLUMN NAME="ISVIP_SOURCE" DATA_TYPE="VARCHAR2"></COLUMN>
<COLUMN NAME="ISVIP_REMARKS" DATA_TYPE="VARCHAR2"></COLUMN>
<COLUMN NAME="IDPROOFNO" DATA_TYPE="VARCHAR2"></COLUMN>
<COLUMN NAME="ADDRESSTYPECD" DATA_TYPE="VARCHAR2"></COLUMN>
<COLUMN NAME="ADDRESS" DATA_TYPE="VARCHAR2"></COLUMN>
<COLUMN NAME="AREACD" DATA_TYPE="VARCHAR2"></COLUMN>
<COLUMN NAME="AREANAME" DATA_TYPE="VARCHAR2"></COLUMN>
<COLUMN NAME="CITYCD" DATA_TYPE="VARCHAR2"></COLUMN>
<COLUMN NAME="CITYNAME" DATA_TYPE="VARCHAR2"></COLUMN>
<COLUMN NAME="DISTRICTCD" DATA_TYPE="VARCHAR2"></COLUMN>
<COLUMN NAME="DISTRICTNAME" DATA_TYPE="VARCHAR2"></COLUMN>
<COLUMN NAME="STATECD" DATA_TYPE="VARCHAR2"></COLUMN>
<COLUMN NAME="STATENAME" DATA_TYPE="VARCHAR2"></COLUMN>
<COLUMN NAME="COUNTRYCD" DATA_TYPE="VARCHAR2"></COLUMN>
<COLUMN NAME="COUNTRYNAME" DATA_TYPE="VARCHAR2"></COLUMN>
<COLUMN NAME="PIN" DATA_TYPE="VARCHAR2"></COLUMN>
<COLUMN NAME="EMAIL" DATA_TYPE="VARCHAR2"></COLUMN>
<COLUMN NAME="TELEPHONE1" DATA_TYPE="VARCHAR2"></COLUMN>
<COLUMN NAME="TELEPHONE2" DATA_TYPE="VARCHAR2"></COLUMN>
<COLUMN NAME="TELEX" DATA_TYPE="VARCHAR2"></COLUMN>
<COLUMN NAME="FAX" DATA_TYPE="VARCHAR2"></COLUMN>
<COLUMN NAME="COMPANY_CODE" DATA_TYPE="VARCHAR2"></COLUMN>
<COLUMN NAME="INTERFACE_TYPE" DATA_TYPE="VARCHAR2"></COLUMN>
<COLUMN NAME="TRAN_KEY" DATA_TYPE="VARCHAR2"></COLUMN>
<COLUMN NAME="RUN_NO" DATA_TYPE="NUMBER"></COLUMN>
<COLUMN NAME="DOCUMENT_HEADER_TEXT" DATA_TYPE="VARCHAR2"></COLUMN>
<COLUMN NAME="NATURE_OF_TRANSACTION" DATA_TYPE="VARCHAR2"></COLUMN>
<COLUMN NAME="BILLNO" DATA_TYPE="VARCHAR2"></COLUMN>
</COLUMNS>
<KEY_COLUMNS>
<COLUMN NAME="TRAN_KEY" DATA_TYPE="VARCHAR2"></COLUMN>
</KEY_COLUMNS>
<FILTER_COLUMNS>
<COLUMN NAME="COALESCE(MODIFYDT,CREATEDT)" DATA_TYPE="DATETIME"></COLUMN>
<COLUMN NAME="PROFIT_CENTER" DATA_TYPE="VARCHAR2"></COLUMN>
<COLUMN NAME="BUSINESS_PLACE" DATA_TYPE="VARCHAR2"></COLUMN>
</FILTER_COLUMNS>
</TABLE>
</ROWSET>